traq_bot/__init__.py
traq_bot/bot.py
traq_bot-1.0.3.dist-info/WHEEL
traq_bot-1.0.3.dist-info/METADATA
traq_bot-1.0.3.dist-info/RECORD
