Metadata-Version: 2.1
Name: traq-bot
Version: 1.0.3
Summary: Bot library for traQ
License: MIT
Author: d_etteiu8383
Author-email: ysdr83@gmail.com
Requires-Python: >=3.9.5,<4.0.0
Classifier: License :: OSI Approved :: MIT License
Classifier: Programming Language :: Python :: 3
Classifier: Programming Language :: Python :: 3.10
